{
  "project_info": {
    "project_number": "565046576541",
    "firebase_url": "https://math-64c88-default-rtdb.asia-southeast1.firebasedatabase.app",
    "project_id": "math-64c88",
    "storage_bucket": "math-64c88.appspot.com"
  },
  "client": [
    {
      "client_info": {
        "mobilesdk_app_id": "1:565046576541:android:ea176a534cf0ad2008db74",
        "android_client_info": {
          "package_name": "com.HCMUS.ARMath"
        }
      },
      "oauth_client": [
        {
          "client_id": "565046576541-0nojt6ki1806hdiv8q4dt0ucenmp1h18.apps.googleusercontent.com",
          "client_type": 3
        }
      ],
      "api_key": [
        {
          "current_key": "AIzaSyBqlw7_xysySkkWsgskSbW943W77ZIAJjI"
        }
      ],
      "services": {
        "appinvite_service": {
          "other_platform_oauth_client": [
            {
              "client_id": "565046576541-0nojt6ki1806hdiv8q4dt0ucenmp1h18.apps.googleusercontent.com",
              "client_type": 3
            },
            {
              "client_id": "565046576541-en7qoeu2ttv3hi1mvevsgilrtd6vgh1j.apps.googleusercontent.com",
              "client_type": 2,
              "ios_info": {
                "bundle_id": "com.KHTN.ARMath"
              }
            }
          ]
        }
      }
    },
    {
      "client_info": {
        "mobilesdk_app_id": "1:565046576541:android:263bac8a72f7322008db74",
        "android_client_info": {
          "package_name": "com.KHTN.AR_Math"
        }
      },
      "oauth_client": [
        {
          "client_id": "565046576541-irsluo63pvbd4jeu9u02pg347n8e7ll2.apps.googleusercontent.com",
          "client_type": 1,
          "android_info": {
            "package_name": "com.KHTN.AR_Math",
            "certificate_hash": "78224fbd2537c2089a0d06f67bb80d1c80fa5b8e"
          }
        },
        {
          "client_id": "565046576541-0nojt6ki1806hdiv8q4dt0ucenmp1h18.apps.googleusercontent.com",
          "client_type": 3
        }
      ],
      "api_key": [
        {
          "current_key": "AIzaSyBqlw7_xysySkkWsgskSbW943W77ZIAJjI"
        }
      ],
      "services": {
        "appinvite_service": {
          "other_platform_oauth_client": [
            {
              "client_id": "565046576541-0nojt6ki1806hdiv8q4dt0ucenmp1h18.apps.googleusercontent.com",
              "client_type": 3
            },
            {
              "client_id": "565046576541-en7qoeu2ttv3hi1mvevsgilrtd6vgh1j.apps.googleusercontent.com",
              "client_type": 2,
              "ios_info": {
                "bundle_id": "com.KHTN.ARMath"
              }
            }
          ]
        }
      }
    }
  ],
  "configuration_version": "1"
}